devin_colors/__init__.py
devin_colors/helper.py
devin_colors/color_maps/BlWhRe.rgb
devin_colors/color_maps/BlueDarkRed18.rgb
devin_colors/color_maps/BlueWhiteOrangeRed.rgb
devin_colors/color_maps/GMT_jet.rgb
devin_colors/color_maps/GMT_red2green.rgb
devin_colors/color_maps/MPL_RdBu.rgb
devin_colors/color_maps/MPL_RdYlGn.rgb
devin_colors/color_maps/MPL_YlGnBu.rgb
devin_colors/color_maps/MPL_bwr.rgb
devin_colors/color_maps/MPL_seismic.rgb
devin_colors/color_maps/MPL_viridis.rgb
devin_colors/color_maps/MPL_winter.rgb
devin_colors/color_maps/NCV_blu_red.rgb
devin_colors/color_maps/NCV_blue_red.rgb
devin_colors/color_maps/NCV_jaisnd.rgb
devin_colors/color_maps/SVG_fs2006.rgb
devin_colors/color_maps/UKM_hadcrut.rgb
devin_colors/color_maps/ViBlGrWhYeOrRe.rgb
devin_colors/color_maps/WhBlGrYeRe.rgb
devin_colors/color_maps/WhViBlGrYeOrRe.rgb
devin_colors/color_maps/WhiteBlueGreenYellowRed.rgb
devin_colors/color_maps/cmp_flux.rgb
devin_colors/color_maps/color_maps.pkl
devin_colors/color_maps/grads_rainbow.rgb
devin_colors/color_maps/ncl_default.rgb
devin_colors/color_maps/precip2_17lev.rgb
devin_colors/color_maps/precip3_16lev.rgb
devin_colors/color_maps/sunshine_diff_12lev.rgb
devin_colors/color_maps/temp_diff_18lev.rgb
devin_colors/color_maps/testcmap.rgb
devin_colors/color_maps/wh-bl-gr-ye-re.rgb
devin_colors-0.1.1.dist-info/LICENSE
devin_colors-0.1.1.dist-info/METADATA
devin_colors-0.1.1.dist-info/WHEEL
devin_colors-0.1.1.dist-info/top_level.txt
devin_colors-0.1.1.dist-info/RECORD
