Metadata-Version: 2.1
Name: devin_colors
Version: 0.1.1
Summary: colors map for python
Home-page: https://github.com/Devin-Long-7/esil
Author: Devin Long
Author-email: long.sc@qq.com
Classifier: Programming Language :: Python :: 3
Classifier: License :: OSI Approved :: MIT License
Classifier: Operating System :: OS Independent
Requires-Python: >=3.6
License-File: LICENSE
Requires-Dist: numpy
Requires-Dist: matplotlib
